{
  "slug": "past-simple",
  "title": "Past Simple Tense",
  "description": "Learn regular and irregular verbs in the past simple",
  "category": "grammar",
  "level": "A1",
  "cefr_level": "a1.1",
  "xp_reward": 25,
  "estimated_minutes": 19,
  "summary_pt_br": "Passado simples — verbos regulares (ed) e irregulares mais comuns do inglês.",
  "sources": [
    {
      "url": "https://learnenglish.britishcouncil.org/grammar/english-grammar-reference/past-simple",
      "title": "British Council — Past Simple",
      "license": "cc-by-nc"
    }
  ],
  "exercises": [
    {
      "id": "pt-001",
      "type": "multiple_choice",
      "question": "I ___ to the supermarket yesterday.",
      "options": [
        "go",
        "goed",
        "went",
        "going"
      ],
      "correct": 2,
      "explanation": "'Go' is an irregular verb. Its past form is 'went'.",
      "hint_pt_br": "'Go' é irregular. O passado é 'went'."
    },
    {
      "id": "pt-002",
      "type": "fill_blank",
      "question": "She ___ (buy) a new dress last week.",
      "correct": "bought",
      "explanation": "'Buy' is irregular: buy → bought.",
      "hint_pt_br": "'Buy' é irregular: buy → bought."
    },
    {
      "id": "pt-003",
      "type": "multiple_choice",
      "question": "We ___ football in the park on Saturday.",
      "options": [
        "play",
        "played",
        "playing",
        "plays"
      ],
      "correct": 1,
      "explanation": "Regular verb: play → played (add -ed).",
      "hint_pt_br": "Verbo regular: play → played (adicione -ed)."
    },
    {
      "id": "pt-004",
      "type": "matching",
      "pairs": [
        [
          "I ate pizza",
          "Eu comi pizza"
        ],
        [
          "She went home",
          "Ela foi para casa"
        ],
        [
          "They watched a movie",
          "Eles assistiram um filme"
        ],
        [
          "He bought shoes",
          "Ele comprou sapatos"
        ]
      ],
      "explanation": "'ate', 'went', 'bought' are irregular. 'watched' is regular.",
      "hint_pt_br": "'ate', 'went', 'bought' são irregulares. 'watched' é regular."
    },
    {
      "id": "pt-005",
      "type": "fill_blank",
      "question": "They ___ (not/go) to the party last night.",
      "correct": "didn't go",
      "explanation": "Negatives in past simple: 'didn't' + base verb.",
      "hint_pt_br": "Negativo no passado: 'didn't' + verbo base."
    }
  ],
  "scenes": [
    {
      "kind": "chapter_title",
      "chapter": "Past Simple Tense",
      "subtitle_en": "Learn regular and irregular verbs in the past simple"
    },
    {
      "kind": "exercise",
      "exercise": {
        "id": "pt-001",
        "type": "multiple_choice",
        "question": "I ___ to the supermarket yesterday.",
        "options": [
          "go",
          "goed",
          "went",
          "going"
        ],
        "correct": 2,
        "explanation": "'Go' is an irregular verb. Its past form is 'went'.",
        "hint_pt_br": "'Go' é irregular. O passado é 'went'."
      }
    },
    {
      "kind": "exercise",
      "exercise": {
        "id": "pt-002",
        "type": "fill_blank",
        "question": "She ___ (buy) a new dress last week.",
        "correct": "bought",
        "explanation": "'Buy' is irregular: buy → bought.",
        "hint_pt_br": "'Buy' é irregular: buy → bought."
      }
    },
    {
      "kind": "exercise",
      "exercise": {
        "id": "pt-003",
        "type": "multiple_choice",
        "question": "We ___ football in the park on Saturday.",
        "options": [
          "play",
          "played",
          "playing",
          "plays"
        ],
        "correct": 1,
        "explanation": "Regular verb: play → played (add -ed).",
        "hint_pt_br": "Verbo regular: play → played (adicione -ed)."
      }
    },
    {
      "kind": "exercise",
      "exercise": {
        "id": "pt-004",
        "type": "matching",
        "pairs": [
          [
            "I ate pizza",
            "Eu comi pizza"
          ],
          [
            "She went home",
            "Ela foi para casa"
          ],
          [
            "They watched a movie",
            "Eles assistiram um filme"
          ],
          [
            "He bought shoes",
            "Ele comprou sapatos"
          ]
        ],
        "explanation": "'ate', 'went', 'bought' are irregular. 'watched' is regular.",
        "hint_pt_br": "'ate', 'went', 'bought' são irregulares. 'watched' é regular."
      }
    },
    {
      "kind": "exercise",
      "exercise": {
        "id": "pt-005",
        "type": "fill_blank",
        "question": "They ___ (not/go) to the party last night.",
        "correct": "didn't go",
        "explanation": "Negatives in past simple: 'didn't' + base verb.",
        "hint_pt_br": "Negativo no passado: 'didn't' + verbo base."
      }
    },
    {
      "kind": "dialog_pronunciation",
      "title": "Past simple drill",
      "character": "Friend",
      "pt_summary": "Past simple em contação de eventos recentes.",
      "turns": [
        {
          "speaker": "ai",
          "text": "What did you do yesterday?",
          "pt": "O que fez ontem?"
        },
        {
          "speaker": "user",
          "target": "I went to the beach with friends.",
          "pt_hint": "WENT (irregular)."
        },
        {
          "speaker": "ai",
          "text": "Did you have fun?",
          "pt": "Se divertiu?"
        },
        {
          "speaker": "user",
          "target": "Yes, we had an amazing time.",
          "pt_hint": "HAD."
        },
        {
          "speaker": "ai",
          "text": "What did you eat?",
          "pt": "O que comeu?"
        },
        {
          "speaker": "user",
          "target": "We ate tacos at Rafa's truck.",
          "pt_hint": "ATE."
        },
        {
          "speaker": "ai",
          "text": "When did you come home?",
          "pt": "Que horas voltou?"
        },
        {
          "speaker": "user",
          "target": "I came home at midnight.",
          "pt_hint": "CAME."
        },
        {
          "speaker": "ai",
          "text": "Did you sleep well after?",
          "pt": "Dormiu bem?"
        },
        {
          "speaker": "user",
          "target": "Yes, I slept like a baby.",
          "pt_hint": "SLEPT."
        },
        {
          "speaker": "ai",
          "text": "Sounds like a perfect day.",
          "pt": "Parece um dia perfeito."
        }
      ]
    },
    {
      "kind": "listening_story",
      "scene_id": "past-simple-listening-story",
      "title": "Listening story — Past Simple Tense",
      "pt_summary": "Ouça a situação com atenção. Depois, escreva em inglês o que você entendeu — resumo, detalhes, seus pensamentos. O professor vai ler e comentar.",
      "prompt_en": "Write in English what you heard. A short summary is fine. Mention who spoke, what they said, and what you think about the situation.",
      "prompt_pt": "Escreva em inglês o que você ouviu. Pode ser um resumo curto. Diga quem falou, o que disseram e o que você achou.",
      "paragraphs": [
        {
          "speaker": "Narrator",
          "voice": "narrator",
          "en": "In this story, we meet Friend and a student. Learn regular and irregular verbs in the past simple Listen carefully and think about what each person says."
        },
        {
          "speaker": "Friend",
          "voice": "female1",
          "en": "What did you do yesterday?"
        },
        {
          "speaker": "The student",
          "voice": "male1",
          "en": "I went to the beach with friends."
        },
        {
          "speaker": "Friend",
          "voice": "female1",
          "en": "Did you have fun?"
        },
        {
          "speaker": "The student",
          "voice": "male1",
          "en": "Yes, we had an amazing time."
        },
        {
          "speaker": "Friend",
          "voice": "female1",
          "en": "What did you eat?"
        },
        {
          "speaker": "The student",
          "voice": "male1",
          "en": "We ate tacos at Rafa's truck."
        },
        {
          "speaker": "Narrator",
          "voice": "narrator",
          "en": "That is the end of our short scene with Friend. Think about what you heard and how the conversation felt."
        }
      ]
    }
  ]
}
