{
  "slug": "burning-down-the-house",
  "title": "Burning Down the House",
  "artist": "Talking Heads",
  "year": 1983,
  "album": "Speaking In Tongues",
  "genre": [
    "rock"
  ],
  "cefr_level": "a2.1",
  "difficulty": "easy",
  "tempo": "mid",
  "duration_seconds": 243,
  "youtube_id": "_3eC35LoF4U",
  "full_lyrics_url": "",
  "full_lyrics_source": "LRCLIB (synced lyrics, fair-use excerpts only)",
  "why_this_song": "Burning Down the House by Talking Heads (1983) — selected for the English-through-music catalog. Use the sing-along prompts and exercises to drill pronunciation, vocabulary, and listening comprehension.",
  "vocab_hooks": [
    {
      "term": "house",
      "pt": "",
      "note": ""
    },
    {
      "term": "burning",
      "pt": "",
      "note": ""
    },
    {
      "term": "fire",
      "pt": "",
      "note": ""
    },
    {
      "term": "might",
      "pt": "",
      "note": ""
    },
    {
      "term": "ordinary",
      "pt": "",
      "note": ""
    }
  ],
  "grammar_callouts": [],
  "timing_source": "lrclib",
  "teaching_notes_md": "## Teaching notes\n\n- Times are estimated from community-synced lyrics and may be off by 1–2 seconds.\n- Start with the sing-along prompt, then move to listen-and-fill.\n- For B1+ students, focus on the discussion questions.\n",
  "copyright_notice": "Short fair-use lyric excerpts only (Brazilian Lei 9.610/98 art. 46 VIII). No full lyrics stored.",
  "sing_along": {
    "prompts": [
      {
        "label_en": "Sing with the chorus",
        "label_pt": "Cante junto no refrão",
        "lines": [
          "Burning down the house",
          "Hold tight",
          "Wait 'til the party's over",
          "Hold tight"
        ],
        "start_seconds": 33,
        "style": "chorus"
      },
      {
        "label_en": "Sing it again — final chorus",
        "label_pt": "Cante de novo — refrão final",
        "lines": [
          "Burning down the house",
          "Ah, it was once upon a place",
          "Sometimes I listen to myself",
          "Gonna come in first place"
        ],
        "start_seconds": 89,
        "style": "chorus"
      }
    ]
  },
  "exercises": [
    {
      "type": "listen_and_fill",
      "prompt_en": "Fill the blank in this line:",
      "prompt_pt": "Complete a lacuna neste verso:",
      "excerpt_before": "You",
      "blank_hint": "word starting with \"m\"",
      "answer": "might",
      "excerpt_after": "get what you're after",
      "youtube_start": 20,
      "youtube_end": 34
    },
    {
      "type": "listen_and_fill",
      "prompt_en": "Fill the blank in this line:",
      "prompt_pt": "Complete a lacuna neste verso:",
      "excerpt_before": "Wait 'til the",
      "blank_hint": "word starting with \"p\"",
      "answer": "partys",
      "excerpt_after": "over",
      "youtube_start": 40,
      "youtube_end": 54
    },
    {
      "type": "listen_and_fill",
      "prompt_en": "Fill the blank in this line:",
      "prompt_pt": "Complete a lacuna neste verso:",
      "excerpt_before": "Time for",
      "blank_hint": "word starting with \"j\"",
      "answer": "jumpin",
      "excerpt_after": "overboard",
      "youtube_start": 58,
      "youtube_end": 72
    },
    {
      "type": "listen_and_fill",
      "prompt_en": "Fill the blank in this line:",
      "prompt_pt": "Complete a lacuna neste verso:",
      "excerpt_before": "Dreams",
      "blank_hint": "word starting with \"w\"",
      "answer": "walking",
      "excerpt_after": "in broad daylight",
      "youtube_start": 81,
      "youtube_end": 95
    },
    {
      "type": "listen_and_fill",
      "prompt_en": "Fill the blank in this line:",
      "prompt_pt": "Complete a lacuna neste verso:",
      "excerpt_before": "Gonna",
      "blank_hint": "word starting with \"b\"",
      "answer": "burst",
      "excerpt_after": "into flames, ah",
      "youtube_start": 107,
      "youtube_end": 121
    },
    {
      "type": "listen_and_fill",
      "prompt_en": "Fill the blank in this line:",
      "prompt_pt": "Complete a lacuna neste verso:",
      "excerpt_before": "Some",
      "blank_hint": "word starting with \"t\"",
      "answer": "things",
      "excerpt_after": "sure can sweep me off my feet",
      "youtube_start": 140,
      "youtube_end": 154
    },
    {
      "type": "translate_line",
      "prompt_en": "Translate this line to Portuguese:",
      "prompt_pt": "Traduza esta linha para português:",
      "excerpt": "You might get what you're after",
      "model_answer_pt": "",
      "teacher_note": "Auto-generated from synced lyrics — add the model translation when reviewing."
    },
    {
      "type": "translate_line",
      "prompt_en": "Translate this line to Portuguese:",
      "prompt_pt": "Traduza esta linha para português:",
      "excerpt": "We're in for nasty weather",
      "model_answer_pt": "",
      "teacher_note": "Auto-generated from synced lyrics — add the model translation when reviewing."
    },
    {
      "type": "translate_line",
      "prompt_en": "Translate this line to Portuguese:",
      "prompt_pt": "Traduza esta linha para português:",
      "excerpt": "Hey, you might need a raincoat",
      "model_answer_pt": "",
      "teacher_note": "Auto-generated from synced lyrics — add the model translation when reviewing."
    },
    {
      "type": "translate_line",
      "prompt_en": "Translate this line to Portuguese:",
      "prompt_pt": "Traduza esta linha para português:",
      "excerpt": "And, baby what do you expect?",
      "model_answer_pt": "",
      "teacher_note": "Auto-generated from synced lyrics — add the model translation when reviewing."
    },
    {
      "type": "translate_line",
      "prompt_en": "Translate this line to Portuguese:",
      "prompt_pt": "Traduza esta linha para português:",
      "excerpt": "And I don't know what you expect",
      "model_answer_pt": "",
      "teacher_note": "Auto-generated from synced lyrics — add the model translation when reviewing."
    },
    {
      "type": "cloze_multi_choice",
      "prompt_en": "Choose the missing word:",
      "prompt_pt": "Escolha a palavra que falta:",
      "excerpt_before": "You",
      "excerpt_after": "get what you're after",
      "options": [
        "babies",
        "fightin",
        "might",
        "ticket"
      ],
      "answer_index": 2,
      "youtube_start": 20,
      "youtube_end": 32
    },
    {
      "type": "cloze_multi_choice",
      "prompt_en": "Choose the missing word:",
      "prompt_pt": "Escolha a palavra que falta:",
      "excerpt_before": "Here's your",
      "excerpt_after": "pack your bags",
      "options": [
        "fightin",
        "partys",
        "strange",
        "ticket"
      ],
      "answer_index": 3,
      "youtube_start": 55,
      "youtube_end": 67
    },
    {
      "type": "cloze_multi_choice",
      "prompt_en": "Choose the missing word:",
      "prompt_pt": "Escolha a palavra que falta:",
      "excerpt_before": "Fightin'",
      "excerpt_after": "with fire",
      "options": [
        "enough",
        "fire",
        "need",
        "people"
      ],
      "answer_index": 1,
      "youtube_start": 70,
      "youtube_end": 82
    },
    {
      "type": "cloze_multi_choice",
      "prompt_en": "Choose the missing word:",
      "prompt_pt": "Escolha a palavra que falta:",
      "excerpt_before": "Gonna come in",
      "excerpt_after": "place",
      "options": [
        "bags",
        "first",
        "stranger",
        "walking"
      ],
      "answer_index": 1,
      "youtube_start": 98,
      "youtube_end": 110
    },
    {
      "type": "cloze_multi_choice",
      "prompt_en": "Choose the missing word:",
      "prompt_pt": "Escolha a palavra que falta:",
      "excerpt_before": "Some",
      "excerpt_after": "sure can sweep me off my feet",
      "options": [
        "babies",
        "need",
        "things",
        "walking"
      ],
      "answer_index": 2,
      "youtube_start": 140,
      "youtube_end": 152
    },
    {
      "type": "unscramble_line",
      "prompt_en": "Put the words in the right order:",
      "prompt_pt": "Coloque as palavras na ordem certa:",
      "shuffled": [
        "you're",
        "might",
        "You",
        "get",
        "what",
        "after"
      ],
      "answer": [
        "You",
        "might",
        "get",
        "what",
        "you're",
        "after"
      ],
      "youtube_start": 20
    },
    {
      "type": "unscramble_line",
      "prompt_en": "Put the words in the right order:",
      "prompt_pt": "Coloque as palavras na ordem certa:",
      "shuffled": [
        "in",
        "nasty",
        "We're",
        "weather",
        "for"
      ],
      "answer": [
        "We're",
        "in",
        "for",
        "nasty",
        "weather"
      ],
      "youtube_start": 44
    },
    {
      "type": "unscramble_line",
      "prompt_en": "Put the words in the right order:",
      "prompt_pt": "Coloque as palavras na ordem certa:",
      "shuffled": [
        "you",
        "are",
        "know",
        "Maybe",
        "where",
        "you"
      ],
      "answer": [
        "Maybe",
        "you",
        "know",
        "where",
        "you",
        "are"
      ],
      "youtube_start": 67
    },
    {
      "type": "unscramble_line",
      "prompt_en": "Put the words in the right order:",
      "prompt_pt": "Coloque as palavras na ordem certa:",
      "shuffled": [
        "in",
        "come",
        "place",
        "Gonna",
        "first"
      ],
      "answer": [
        "Gonna",
        "come",
        "in",
        "first",
        "place"
      ],
      "youtube_start": 98
    },
    {
      "type": "unscramble_line",
      "prompt_en": "Put the words in the right order:",
      "prompt_pt": "Coloque as palavras na ordem certa:",
      "shuffled": [
        "Don't",
        "hurt",
        "nobody",
        "wannna"
      ],
      "answer": [
        "Don't",
        "wannna",
        "hurt",
        "nobody"
      ],
      "youtube_start": 137
    },
    {
      "type": "count_word",
      "prompt_en": "How many times do you hear the word \"house\" in the whole song?",
      "prompt_pt": "Quantas vezes você ouve a palavra \"house\" na música inteira?",
      "word": "house",
      "answer": 6
    },
    {
      "type": "count_word",
      "prompt_en": "How many times do you hear the word \"burning\" in the whole song?",
      "prompt_pt": "Quantas vezes você ouve a palavra \"burning\" na música inteira?",
      "word": "burning",
      "answer": 5
    },
    {
      "type": "line_order",
      "prompt_en": "Put these three lines in the order they appear in the song:",
      "prompt_pt": "Coloque estes três versos na ordem em que aparecem na música:",
      "excerpts": [
        {
          "text": "Ah, watch out",
          "order": 0
        },
        {
          "text": "Transportation is here",
          "order": 1
        },
        {
          "text": "People on their way to work",
          "order": 2
        }
      ]
    },
    {
      "type": "line_order",
      "prompt_en": "And these three — put them in the order they appear in the song:",
      "prompt_pt": "E estes três — coloque na ordem em que aparecem na música:",
      "excerpts": [
        {
          "text": "You might get what you're after",
          "order": 0
        },
        {
          "text": "Hey, you might need a raincoat",
          "order": 1
        },
        {
          "text": "Gonna burst into flames, ah",
          "order": 2
        }
      ]
    },
    {
      "type": "discussion",
      "prompt_en": "If you could change the ending of the story told in \"Burning Down the House\", what would happen instead?",
      "prompt_pt": "Se você pudesse mudar o final da história contada em \"Burning Down the House\", o que aconteceria?",
      "target_vocab": [
        "house",
        "burning",
        "fire",
        "might"
      ]
    },
    {
      "type": "discussion",
      "prompt_en": "Describe the mood of \"Burning Down the House\" in three adjectives. What part of the song makes you feel that way?",
      "prompt_pt": "Descreva o clima de \"Burning Down the House\" em três adjetivos. Que parte da música te faz sentir isso?",
      "target_vocab": [
        "house",
        "burning",
        "fire",
        "might"
      ]
    },
    {
      "type": "discussion",
      "prompt_en": "Who in your life would you dedicate \"Burning Down the House\" to, and what line captures what you want to say to them?",
      "prompt_pt": "Para quem da sua vida você dedicaria \"Burning Down the House\", e qual verso resume o que você quer dizer para essa pessoa?",
      "target_vocab": [
        "house",
        "burning",
        "fire",
        "might"
      ]
    },
    {
      "type": "spot_the_grammar",
      "prompt_en": "Write the full form of each contraction:",
      "prompt_pt": "Escreva a forma completa de cada contração:",
      "expected": [
        {
          "short": "you're",
          "full": "you are"
        },
        {
          "short": "i'm",
          "full": "I am"
        },
        {
          "short": "we're",
          "full": "we are"
        },
        {
          "short": "gonna",
          "full": "going to"
        },
        {
          "short": "that's",
          "full": "that is"
        },
        {
          "short": "don't",
          "full": "do not"
        }
      ]
    }
  ]
}
