{
  "slug": "this-love",
  "title": "This Love",
  "artist": "Maroon 5",
  "year": 2002,
  "album": "Songs About Jane",
  "genre": [
    "pop"
  ],
  "cefr_level": "a2.2",
  "difficulty": "easy",
  "tempo": "mid",
  "duration_seconds": 207,
  "youtube_id": "XPpTgCho5ZA",
  "full_lyrics_url": "",
  "full_lyrics_source": "LRCLIB (synced lyrics, fair-use excerpts only)",
  "why_this_song": "This Love by Maroon 5 (2002) — selected for the English-through-music catalog. Use the sing-along prompts and exercises to drill pronunciation, vocabulary, and listening comprehension.",
  "vocab_hooks": [
    {
      "term": "goodbye",
      "pt": "",
      "note": "Appears 11 times; first heard in: \"Whispered goodbye as she got on a plane\""
    },
    {
      "term": "heart",
      "pt": "",
      "note": "Appears 6 times; first heard in: \"Never to return again but always in my heart, oh\""
    },
    {
      "term": "many",
      "pt": "",
      "note": "Appears 6 times; first heard in: \"She said goodbye too many times before\""
    },
    {
      "term": "times",
      "pt": "",
      "note": "Appears 6 times; first heard in: \"She said goodbye too many times before\""
    },
    {
      "term": "taken",
      "pt": "",
      "note": "Appears 5 times; first heard in: \"This love has taken its toll on me\""
    }
  ],
  "grammar_callouts": [],
  "timing_source": "lrclib",
  "teaching_notes_md": "## Teaching notes\n\n- Times are estimated from community-synced lyrics and may be off by 1–2 seconds.\n- Start with the sing-along prompt, then move to listen-and-fill.\n- For B1+ students, focus on the discussion questions.\n",
  "copyright_notice": "Short fair-use lyric excerpts only (Brazilian Lei 9.610/98 art. 46 VIII). No full lyrics stored.",
  "sing_along": {
    "prompts": [
      {
        "label_en": "Sing with the chorus",
        "label_pt": "Cante junto no refrão",
        "lines": [
          "She said goodbye too many times before",
          "And her heart is breakin' in front of me",
          "And I have no choice",
          "'Cause I won't say goodbye anymore"
        ],
        "start_seconds": 45,
        "style": "chorus"
      },
      {
        "label_en": "Sing it again — final chorus",
        "label_pt": "Cante de novo — refrão final",
        "lines": [
          "She said goodbye too many times before",
          "And my heart is breakin' in front of me",
          "And she said goodbye too many times before"
        ],
        "start_seconds": 166,
        "style": "chorus"
      }
    ]
  },
  "exercises": [
    {
      "type": "listen_and_fill",
      "prompt_en": "Fill the blank in this line:",
      "prompt_pt": "Complete a lacuna neste verso:",
      "excerpt_before": "The fire",
      "blank_hint": "word starting with \"b\"",
      "answer": "burning",
      "excerpt_after": "in her eyes",
      "youtube_start": 23,
      "youtube_end": 37
    },
    {
      "type": "listen_and_fill",
      "prompt_en": "Fill the blank in this line:",
      "prompt_pt": "Complete a lacuna neste verso:",
      "excerpt_before": "Whispered",
      "blank_hint": "word starting with \"g\"",
      "answer": "goodbye",
      "excerpt_after": "as she got on a plane",
      "youtube_start": 30,
      "youtube_end": 44
    },
    {
      "type": "listen_and_fill",
      "prompt_en": "Fill the blank in this line:",
      "prompt_pt": "Complete a lacuna neste verso:",
      "excerpt_before": "And her",
      "blank_hint": "word starting with \"h\"",
      "answer": "heart",
      "excerpt_after": "is breakin' in front of me",
      "youtube_start": 50,
      "youtube_end": 64
    },
    {
      "type": "listen_and_fill",
      "prompt_en": "Fill the blank in this line:",
      "prompt_pt": "Complete a lacuna neste verso:",
      "excerpt_before": "Keep her",
      "blank_hint": "word starting with \"c\"",
      "answer": "coming",
      "excerpt_after": "every night",
      "youtube_start": 74,
      "youtube_end": 88
    },
    {
      "type": "listen_and_fill",
      "prompt_en": "Fill the blank in this line:",
      "prompt_pt": "Complete a lacuna neste verso:",
      "excerpt_before": "Then turn around and",
      "blank_hint": "word starting with \"l\"",
      "answer": "leave",
      "excerpt_after": "again, but uh-oh",
      "youtube_start": 86,
      "youtube_end": 100
    },
    {
      "type": "listen_and_fill",
      "prompt_en": "Fill the blank in this line:",
      "prompt_pt": "Complete a lacuna neste verso:",
      "excerpt_before": "I'll fix",
      "blank_hint": "word starting with \"t\"",
      "answer": "these",
      "excerpt_after": "broken things, repair your broken wings",
      "youtube_start": 121,
      "youtube_end": 135
    },
    {
      "type": "translate_line",
      "prompt_en": "Translate this line to Portuguese:",
      "prompt_pt": "Traduza esta linha para português:",
      "excerpt": "I was so high, I did not recognize",
      "model_answer_pt": "",
      "teacher_note": "Auto-generated from synced lyrics — add the model translation when reviewing."
    },
    {
      "type": "translate_line",
      "prompt_en": "Translate this line to Portuguese:",
      "prompt_pt": "Traduza esta linha para português:",
      "excerpt": "She said goodbye too many times before",
      "model_answer_pt": "",
      "teacher_note": "Auto-generated from synced lyrics — add the model translation when reviewing."
    },
    {
      "type": "translate_line",
      "prompt_en": "Translate this line to Portuguese:",
      "prompt_pt": "Traduza esta linha para português:",
      "excerpt": "'Cause I won't say goodbye anymore",
      "model_answer_pt": "",
      "teacher_note": "Auto-generated from synced lyrics — add the model translation when reviewing."
    },
    {
      "type": "translate_line",
      "prompt_en": "Translate this line to Portuguese:",
      "prompt_pt": "Traduza esta linha para português:",
      "excerpt": "Every inch of you",
      "model_answer_pt": "",
      "teacher_note": "Auto-generated from synced lyrics — add the model translation when reviewing."
    },
    {
      "type": "translate_line",
      "prompt_en": "Translate this line to Portuguese:",
      "prompt_pt": "Traduza esta linha para português:",
      "excerpt": "The fire burning in her eyes",
      "model_answer_pt": "",
      "teacher_note": "Auto-generated from synced lyrics — add the model translation when reviewing."
    },
    {
      "type": "cloze_multi_choice",
      "prompt_en": "Choose the missing word:",
      "prompt_pt": "Escolha a palavra que falta:",
      "excerpt_before": "I was so",
      "excerpt_after": "I did not recognize",
      "options": [
        "high",
        "mind",
        "taken",
        "whoa"
      ],
      "answer_index": 0,
      "youtube_start": 20,
      "youtube_end": 32
    },
    {
      "type": "cloze_multi_choice",
      "prompt_en": "Choose the missing word:",
      "prompt_pt": "Escolha a palavra que falta:",
      "excerpt_before": "This love has",
      "excerpt_after": "its toll on me",
      "options": [
        "breakin",
        "heart",
        "taken",
        "uh-oh"
      ],
      "answer_index": 2,
      "youtube_start": 41,
      "youtube_end": 53
    },
    {
      "type": "cloze_multi_choice",
      "prompt_en": "Choose the missing word:",
      "prompt_pt": "Escolha a palavra que falta:",
      "excerpt_before": "I",
      "excerpt_after": "my best to feed her appetite",
      "options": [
        "cause",
        "every",
        "times",
        "tried"
      ],
      "answer_index": 3,
      "youtube_start": 71,
      "youtube_end": 83
    },
    {
      "type": "cloze_multi_choice",
      "prompt_en": "Choose the missing word:",
      "prompt_pt": "Escolha a palavra que falta:",
      "excerpt_before": "Pretending to",
      "excerpt_after": "the same",
      "options": [
        "choice",
        "feel",
        "mind",
        "taken"
      ],
      "answer_index": 1,
      "youtube_start": 84,
      "youtube_end": 96
    },
    {
      "type": "cloze_multi_choice",
      "prompt_en": "Choose the missing word:",
      "prompt_pt": "Escolha a palavra que falta:",
      "excerpt_before": "And her heart is",
      "excerpt_after": "in front of me",
      "options": [
        "breakin",
        "plane",
        "recognize",
        "whispered"
      ],
      "answer_index": 0,
      "youtube_start": 101,
      "youtube_end": 113
    },
    {
      "type": "unscramble_line",
      "prompt_en": "Put the words in the right order:",
      "prompt_pt": "Coloque as palavras na ordem certa:",
      "shuffled": [
        "her",
        "The",
        "eyes",
        "burning",
        "fire",
        "in"
      ],
      "answer": [
        "The",
        "fire",
        "burning",
        "in",
        "her",
        "eyes"
      ],
      "youtube_start": 23
    },
    {
      "type": "unscramble_line",
      "prompt_en": "Put the words in the right order:",
      "prompt_pt": "Coloque as palavras na ordem certa:",
      "shuffled": [
        "The",
        "my",
        "mind",
        "controlled",
        "that",
        "chaos"
      ],
      "answer": [
        "The",
        "chaos",
        "that",
        "controlled",
        "my",
        "mind"
      ],
      "youtube_start": 26
    },
    {
      "type": "unscramble_line",
      "prompt_en": "Put the words in the right order:",
      "prompt_pt": "Coloque as palavras na ordem certa:",
      "shuffled": [
        "choice",
        "have",
        "I",
        "no",
        "And"
      ],
      "answer": [
        "And",
        "I",
        "have",
        "no",
        "choice"
      ],
      "youtube_start": 55
    },
    {
      "type": "unscramble_line",
      "prompt_en": "Put the words in the right order:",
      "prompt_pt": "Coloque as palavras na ordem certa:",
      "shuffled": [
        "her",
        "coming",
        "Keep",
        "night",
        "every"
      ],
      "answer": [
        "Keep",
        "her",
        "coming",
        "every",
        "night"
      ],
      "youtube_start": 74
    },
    {
      "type": "unscramble_line",
      "prompt_en": "Put the words in the right order:",
      "prompt_pt": "Coloque as palavras na ordem certa:",
      "shuffled": [
        "to",
        "same",
        "Pretending",
        "feel",
        "the"
      ],
      "answer": [
        "Pretending",
        "to",
        "feel",
        "the",
        "same"
      ],
      "youtube_start": 84
    },
    {
      "type": "count_word",
      "prompt_en": "How many times do you hear the word \"goodbye\" in the whole song?",
      "prompt_pt": "Quantas vezes você ouve a palavra \"goodbye\" na música inteira?",
      "word": "goodbye",
      "answer": 11
    },
    {
      "type": "count_word",
      "prompt_en": "How many times do you hear the word \"heart\" in the whole song?",
      "prompt_pt": "Quantas vezes você ouve a palavra \"heart\" na música inteira?",
      "word": "heart",
      "answer": 6
    },
    {
      "type": "line_order",
      "prompt_en": "Put these three lines in the order they appear in the song:",
      "prompt_pt": "Coloque estes três versos na ordem em que aparecem na música:",
      "excerpts": [
        {
          "text": "I was so high, I did not recognize",
          "order": 0
        },
        {
          "text": "So hard to keep her satisfied, oh",
          "order": 1
        },
        {
          "text": "Her heart is breakin' in front of me",
          "order": 2
        }
      ]
    },
    {
      "type": "line_order",
      "prompt_en": "And these three — put them in the order they appear in the song:",
      "prompt_pt": "E estes três — coloque na ordem em que aparecem na música:",
      "excerpts": [
        {
          "text": "The fire burning in her eyes",
          "order": 0
        },
        {
          "text": "She said goodbye too many times before",
          "order": 1
        },
        {
          "text": "And I have no choice",
          "order": 2
        }
      ]
    },
    {
      "type": "discussion",
      "prompt_en": "Which single word from this song do you think carries the most emotional weight, and why?",
      "prompt_pt": "Qual palavra dessa música carrega mais peso emocional para você, e por quê?",
      "target_vocab": [
        "goodbye",
        "heart",
        "many",
        "times"
      ]
    },
    {
      "type": "discussion",
      "prompt_en": "\"This Love\" was released in 2002. Do you think the themes in the song are timeless, or do they feel dated? Give one example from the lyrics.",
      "prompt_pt": "\"This Love\" foi lançada em 2002. Você acha que os temas da música são atemporais ou já parecem datados? Dê um exemplo do que ouviu.",
      "target_vocab": [
        "goodbye",
        "heart",
        "many",
        "times"
      ]
    },
    {
      "type": "discussion",
      "prompt_en": "Imagine you are making a short film with \"This Love\" as the soundtrack. What scene would you show while the chorus plays?",
      "prompt_pt": "Imagine que você vai fazer um curta com \"This Love\" como trilha sonora. Que cena você mostraria no momento do refrão?",
      "target_vocab": [
        "goodbye",
        "heart",
        "many",
        "times"
      ]
    },
    {
      "type": "spot_the_grammar",
      "prompt_en": "Write the full form of each contraction:",
      "prompt_pt": "Escreva a forma completa de cada contração:",
      "expected": [
        {
          "short": "won't",
          "full": "will not"
        },
        {
          "short": "i'll",
          "full": "I will"
        },
        {
          "short": "it's",
          "full": "it is"
        },
        {
          "short": "i'm",
          "full": "I am"
        },
        {
          "short": "that's",
          "full": "that is"
        }
      ]
    }
  ]
}
